{
    "title": {
        "en": "Todos los Colores",
        "es": "Todos los Colores"
    },
    "category": {
        "en": "Feature Film",
        "es": "Largometraje"
    },
    "director": "Beatriz de Silva",
    "synopsis": {
        "en": "Coming in 2026. An emotional and luminous coming-of-age comedy about adolescence, desire, and the search for identity. Following 17-year-old Belén, a young wheelchair user who confronts her fears and desires as she joins an athletics club.",
        "es": "Próximamente en 2026. Una comedia emocional y luminosa sobre la adolescencia, el deseo y la búsqueda de identidad. Sigue a Belén, una joven de 17 años en silla de ruedas que se enfrenta a sus miedos y deseos al unirse a un club de atletismo."
    },
    "image": "",
    "video": "",
    "featured": false,
    "stills": []
}